ssbtoolkit/HuTRdb.sqlite3
ssbtoolkit/Utils.py
ssbtoolkit/__init__.py
ssbtoolkit/pathways/Gi.py
ssbtoolkit/pathways/Gi_parameters.csv
ssbtoolkit/pathways/Gi_reactions.csv
ssbtoolkit/pathways/Gq.py
ssbtoolkit/pathways/Gq_parameters.csv
ssbtoolkit/pathways/Gq_reactions.csv
ssbtoolkit/pathways/Gs.py
ssbtoolkit/pathways/Gs_parameters.csv
ssbtoolkit/pathways/Gs_reactions.csv
ssbtoolkit/pathways/OXTR_pathway.py
ssbtoolkit/pathways/OXTR_pathway_parameters.csv
ssbtoolkit/pathways/OXTR_pathway_reactions.csv
ssbtoolkit/pathways/OXTR_pathway_testing.py
ssbtoolkit/pathways/__init__.py
ssbtoolkit-1.0.9.dist-info/METADATA
ssbtoolkit-1.0.9.dist-info/WHEEL
ssbtoolkit-1.0.9.dist-info/top_level.txt
ssbtoolkit-1.0.9.dist-info/RECORD
